report_not_covered_lines/__init__.py
report_not_covered_lines/__main__.py
report_not_covered_lines/report_not_covered_lines.py
report_not_covered_lines-0.0.3.dist-info/LICENSE
report_not_covered_lines-0.0.3.dist-info/METADATA
report_not_covered_lines-0.0.3.dist-info/WHEEL
report_not_covered_lines-0.0.3.dist-info/entry_points.txt
report_not_covered_lines-0.0.3.dist-info/top_level.txt
report_not_covered_lines-0.0.3.dist-info/RECORD
